fast_dep-0.0.4.dist-info/METADATA
fast_dep-0.0.4.dist-info/WHEEL
fast_dep-0.0.4.dist-info/license_files/LICENSE.md
fast_dep/__init__.py
fast_dep/__init__.pyi
fast_dep/py.typed
fast_dep/fast_dep.pypy39-pp73-aarch64-linux-gnu.so
fast_dep-0.0.4.dist-info/RECORD
