Metadata-Version: 2.1
Name: fast_dep
Version: 0.0.4
Classifier: Programming Language :: Rust
Classifier: Programming Language :: Python :: Implementation :: CPython
Classifier: Programming Language :: Python :: Implementation :: PyPy
Requires-Dist: pytest ; extra == 'test'
Requires-Dist: pytest-mock ; extra == 'test'
Requires-Dist: pytest-unordered ; extra == 'test'
Provides-Extra: test
License-File: LICENSE.md
Summary: Fast python depdency tracing.
Author: Carter Fendley
License: MIT
Requires-Python: >=3.7
